ask_questions/__init__.py
ask_questions/ask_questions.py
marker/__init__.py
marker/marker.py
marker/adapter/__init__.py
marker/adapter/adapter.py
marker/adapter/adapter_server.py
marker/command_line_tool/__init__.py
marker/command_line_tool/dsl.py
marker/command_line_tool/instruction.py
marker/command_line_tool/main.py
marker/command_line_tool/utils.py
marker/command_line_tool/tests/__init__.py
marker/command_line_tool/tests/test_utils.py
marker/marker/__init__.py
marker/marker/interpreter.py
marker/marker/main.py
marker/mymark/__init__.py
marker/mymark/mymark/__init__.py
marker/mymark/mymark/mymark.py
src/__init__.py
src/adapter/__init__.py
src/adapter/adapter.py
src/adapter/adapter_gpt.py
src/adapter/test_adapter.py
src/command_line_tool/__init__.py
src/command_line_tool/answer_questions.py
src/command_line_tool/dsl.py
src/command_line_tool/instruction.py
src/command_line_tool/main.py
src/command_line_tool/utils.py
src/command_line_tool/tests/__init__.py
src/command_line_tool/tests/test_utils.py
src/marker/__init__.py
src/marker/interpreter.py
src/marker/main.py
src/marker/auto_marker/__init__.py
src/marker/auto_marker/auto_marker.py
src/marker/auto_marker/mark.py
mymark-1.1.1.dist-info/METADATA
mymark-1.1.1.dist-info/WHEEL
mymark-1.1.1.dist-info/entry_points.txt
mymark-1.1.1.dist-info/top_level.txt
mymark-1.1.1.dist-info/RECORD
