Metadata-Version: 2.1
Name: mymark
Version: 1.1.1
Summary: UNKNOWN
Home-page: UNKNOWN
License: UNKNOWN
Platform: UNKNOWN
Requires-Dist: aiohttp
Requires-Dist: pytest
Requires-Dist: pylint
Requires-Dist: mypy
